{
    "history":  [
                    {
                        "slug":  "money-aipa-landing-page",
                        "time":  "2026-06-03T15:07:02.1548768+09:00"
                    },
                    {
                        "slug":  "money-aipax-proposal-template",
                        "time":  "2026-06-03T15:10:02.1535883+09:00"
                    },
                    {
                        "slug":  "money-content-school",
                        "time":  "2026-06-03T15:13:02.1060955+09:00"
                    },
                    {
                        "slug":  "money-dinii-followup",
                        "time":  "2026-06-03T15:16:02.1479786+09:00"
                    },
                    {
                        "slug":  "money-seo-aipa",
                        "time":  "2026-06-03T15:19:02.1764343+09:00"
                    },
                    {
                        "slug":  "money-contest-list",
                        "time":  "2026-06-03T15:22:02.1648455+09:00"
                    },
                    {
                        "slug":  "money-app-niche-hunt",
                        "time":  "2026-06-03T15:25:02.1065711+09:00"
                    },
                    {
                        "slug":  "money-school-trial",
                        "time":  "2026-06-03T15:28:02.1366493+09:00"
                    },
                    {
                        "slug":  "money-school-parent-lp",
                        "time":  "2026-06-03T15:31:02.2848849+09:00"
                    },
                    {
                        "slug":  "money-aipa-prospect-list",
                        "time":  "2026-06-03T15:34:02.1844593+09:00"
                    },
                    {
                        "slug":  "money-contest-yume-award",
                        "time":  "2026-06-03T15:37:02.1666960+09:00"
                    },
                    {
                        "slug":  "money-twitter-aipax",
                        "time":  "2026-06-03T15:40:02.2436808+09:00"
                    },
                    {
                        "slug":  "money-aipax-prospects",
                        "time":  "2026-06-03T15:43:02.2334306+09:00"
                    },
                    {
                        "slug":  "money-aipa-followup-scripts",
                        "time":  "2026-06-03T15:46:02.2223424+09:00"
                    },
                    {
                        "slug":  "money-app-spec-1week",
                        "time":  "2026-06-03T15:49:02.2558549+09:00"
                    },
                    {
                        "slug":  "money-school-curriculum",
                        "time":  "2026-06-03T15:52:02.2731870+09:00"
                    },
                    {
                        "slug":  "money-aipa-email-templates",
                        "time":  "2026-06-03T15:55:02.2698123+09:00"
                    },
                    {
                        "slug":  "money-school-curriculum",
                        "time":  "2026-06-03T15:58:02.2812517+09:00"
                    },
                    {
                        "slug":  "money-aipa-email-templates",
                        "time":  "2026-06-03T16:01:02.2197713+09:00"
                    },
                    {
                        "slug":  "money-app-spec-1week",
                        "time":  "2026-06-03T16:04:02.2341907+09:00"
                    },
                    {
                        "slug":  "money-content-school",
                        "time":  "2026-06-03T16:07:02.4072260+09:00"
                    },
                    {
                        "slug":  "money-aipax-prospects",
                        "time":  "2026-06-03T16:10:02.3193810+09:00"
                    },
                    {
                        "slug":  "money-school-trial",
                        "time":  "2026-06-03T16:13:02.2704503+09:00"
                    },
                    {
                        "slug":  "money-aipa-followup-scripts",
                        "time":  "2026-06-03T16:16:02.3146184+09:00"
                    },
                    {
                        "slug":  "money-aipax-prospects",
                        "time":  "2026-06-03T16:19:02.3208497+09:00"
                    },
                    {
                        "slug":  "money-app-spec-1week",
                        "time":  "2026-06-03T16:22:02.2986743+09:00"
                    },
                    {
                        "slug":  "money-app-niche-hunt",
                        "time":  "2026-06-03T16:25:02.3073522+09:00"
                    },
                    {
                        "slug":  "money-app-spec-1week",
                        "time":  "2026-06-03T16:28:02.2971973+09:00"
                    },
                    {
                        "slug":  "money-app-spec-1week",
                        "time":  "2026-06-03T16:31:02.3281827+09:00"
                    },
                    {
                        "slug":  "money-content-school",
                        "time":  "2026-06-03T16:34:02.3253976+09:00"
                    },
                    {
                        "slug":  "money-aipax-prospects",
                        "time":  "2026-06-03T16:37:02.2989295+09:00"
                    },
                    {
                        "slug":  "money-dinii-followup",
                        "time":  "2026-06-03T16:40:02.3447186+09:00"
                    },
                    {
                        "slug":  "money-aipa-prospect-list",
                        "time":  "2026-06-03T16:43:02.4011585+09:00"
                    },
                    {
                        "slug":  "money-aipa-prospect-list",
                        "time":  "2026-06-03T16:46:02.3585352+09:00"
                    },
                    {
                        "slug":  "money-dinii-followup",
                        "time":  "2026-06-03T16:49:02.3222307+09:00"
                    },
                    {
                        "slug":  "money-app-spec-1week",
                        "time":  "2026-06-03T16:52:02.2579215+09:00"
                    },
                    {
                        "slug":  "money-school-trial",
                        "time":  "2026-06-03T16:55:02.4723148+09:00"
                    },
                    {
                        "slug":  "money-app-spec-1week",
                        "time":  "2026-06-03T16:58:02.4429457+09:00"
                    },
                    {
                        "slug":  "money-aipax-prospects",
                        "time":  "2026-06-03T17:01:02.3668570+09:00"
                    },
                    {
                        "slug":  "money-aipa-prospect-list",
                        "time":  "2026-06-03T17:04:02.4439027+09:00"
                    },
                    {
                        "slug":  "money-content-school",
                        "time":  "2026-06-03T17:07:02.4602925+09:00"
                    },
                    {
                        "slug":  "money-school-trial",
                        "time":  "2026-06-03T17:10:02.3689163+09:00"
                    },
                    {
                        "slug":  "money-aipax-prospects",
                        "time":  "2026-06-03T17:13:02.4120301+09:00"
                    },
                    {
                        "slug":  "money-aipa-landing-page",
                        "time":  "2026-06-03T17:16:02.4634539+09:00"
                    },
                    {
                        "slug":  "money-aipa-followup-scripts",
                        "time":  "2026-06-03T17:19:02.5145506+09:00"
                    },
                    {
                        "slug":  "money-dinii-followup",
                        "time":  "2026-06-03T17:22:02.4979559+09:00"
                    },
                    {
                        "slug":  "money-aipa-landing-page",
                        "time":  "2026-06-03T17:25:02.3927342+09:00"
                    },
                    {
                        "slug":  "money-school-curriculum",
                        "time":  "2026-06-03T17:28:02.4772598+09:00"
                    },
                    {
                        "slug":  "money-content-school",
                        "time":  "2026-06-03T17:31:02.5066108+09:00"
                    },
                    {
                        "slug":  "money-contest-list",
                        "time":  "2026-06-03T17:34:02.4829576+09:00"
                    },
                    {
                        "slug":  "money-aipax-proposal-template",
                        "time":  "2026-06-03T17:37:02.5004104+09:00"
                    },
                    {
                        "slug":  "money-aipa-landing-page",
                        "time":  "2026-06-03T17:40:02.5503490+09:00"
                    },
                    {
                        "slug":  "money-app-niche-hunt",
                        "time":  "2026-06-03T17:43:02.6000967+09:00"
                    },
                    {
                        "slug":  "money-twitter-aipax",
                        "time":  "2026-06-03T17:46:02.5666941+09:00"
                    },
                    {
                        "slug":  "money-aipa-landing-page",
                        "time":  "2026-06-03T17:49:02.5473599+09:00"
                    },
                    {
                        "slug":  "money-contest-yume-award",
                        "time":  "2026-06-03T17:52:02.5384938+09:00"
                    },
                    {
                        "slug":  "money-app-niche-hunt",
                        "time":  "2026-06-03T17:55:02.6098455+09:00"
                    },
                    {
                        "slug":  "money-aipax-proposal-template",
                        "time":  "2026-06-03T17:58:02.5424545+09:00"
                    },
                    {
                        "slug":  "money-school-curriculum",
                        "time":  "2026-06-03T18:01:02.5283182+09:00"
                    },
                    {
                        "slug":  "money-school-curriculum",
                        "time":  "2026-06-03T18:04:02.5440171+09:00"
                    },
                    {
                        "slug":  "money-dinii-followup",
                        "time":  "2026-06-03T18:07:01.5187582+09:00"
                    },
                    {
                        "slug":  "money-app-niche-hunt",
                        "time":  "2026-06-03T18:10:01.5337808+09:00"
                    },
                    {
                        "slug":  "money-aipa-landing-page",
                        "time":  "2026-06-03T18:13:01.5728709+09:00"
                    },
                    {
                        "slug":  "money-app-niche-hunt",
                        "time":  "2026-06-03T18:16:01.5540451+09:00"
                    },
                    {
                        "slug":  "money-app-niche-hunt",
                        "time":  "2026-06-03T18:19:01.5569468+09:00"
                    },
                    {
                        "slug":  "money-aipa-followup-scripts",
                        "time":  "2026-06-03T18:22:01.5670833+09:00"
                    },
                    {
                        "slug":  "money-twitter-aipax",
                        "time":  "2026-06-03T18:25:01.5360859+09:00"
                    },
                    {
                        "slug":  "money-aipa-email-templates",
                        "time":  "2026-06-03T18:28:01.5569512+09:00"
                    },
                    {
                        "slug":  "money-school-curriculum",
                        "time":  "2026-06-03T18:31:01.5642807+09:00"
                    },
                    {
                        "slug":  "money-school-curriculum",
                        "time":  "2026-06-03T18:34:01.6248215+09:00"
                    },
                    {
                        "slug":  "money-aipa-followup-scripts",
                        "time":  "2026-06-03T18:37:01.5800382+09:00"
                    },
                    {
                        "slug":  "money-dinii-followup",
                        "time":  "2026-06-03T18:40:01.5977244+09:00"
                    },
                    {
                        "slug":  "money-school-curriculum",
                        "time":  "2026-06-03T18:43:01.5903325+09:00"
                    },
                    {
                        "slug":  "money-school-trial",
                        "time":  "2026-06-03T18:46:01.6088145+09:00"
                    },
                    {
                        "slug":  "money-content-school",
                        "time":  "2026-06-03T18:49:01.6006790+09:00"
                    },
                    {
                        "slug":  "money-school-trial",
                        "time":  "2026-06-03T18:52:01.6305423+09:00"
                    },
                    {
                        "slug":  "money-app-niche-hunt",
                        "time":  "2026-06-03T18:55:01.5912133+09:00"
                    },
                    {
                        "slug":  "money-school-parent-lp",
                        "time":  "2026-06-03T18:58:01.6162456+09:00"
                    },
                    {
                        "slug":  "money-contest-yume-award",
                        "time":  "2026-06-03T19:01:01.6202553+09:00"
                    },
                    {
                        "slug":  "money-school-curriculum",
                        "time":  "2026-06-03T19:04:01.6667163+09:00"
                    },
                    {
                        "slug":  "money-aipax-prospects",
                        "time":  "2026-06-03T19:07:01.6992973+09:00"
                    },
                    {
                        "slug":  "money-aipax-prospects",
                        "time":  "2026-06-03T19:10:01.6923994+09:00"
                    },
                    {
                        "slug":  "money-aipax-proposal-template",
                        "time":  "2026-06-03T19:13:01.7057424+09:00"
                    },
                    {
                        "slug":  "money-school-trial",
                        "time":  "2026-06-03T19:16:01.8113023+09:00"
                    },
                    {
                        "slug":  "money-aipax-proposal-template",
                        "time":  "2026-06-03T19:19:01.6912122+09:00"
                    },
                    {
                        "slug":  "money-seo-aipa",
                        "time":  "2026-06-03T19:22:01.7257729+09:00"
                    },
                    {
                        "slug":  "money-twitter-aipax",
                        "time":  "2026-06-03T19:25:01.6993536+09:00"
                    },
                    {
                        "slug":  "money-contest-list",
                        "time":  "2026-06-03T19:28:01.7589072+09:00"
                    },
                    {
                        "slug":  "money-content-school",
                        "time":  "2026-06-03T19:31:01.7244885+09:00"
                    },
                    {
                        "slug":  "money-aipa-prospect-list",
                        "time":  "2026-06-03T19:34:01.6355145+09:00"
                    },
                    {
                        "slug":  "money-school-trial",
                        "time":  "2026-06-03T19:37:01.6960129+09:00"
                    },
                    {
                        "slug":  "money-app-spec-1week",
                        "time":  "2026-06-03T19:40:01.6855028+09:00"
                    },
                    {
                        "slug":  "money-content-school",
                        "time":  "2026-06-03T20:07:01.8222039+09:00"
                    },
                    {
                        "slug":  "money-aipa-email-templates",
                        "time":  "2026-06-03T20:31:01.9178977+09:00"
                    },
                    {
                        "slug":  "money-aipax-proposal-template",
                        "time":  "2026-06-03T20:55:01.8922314+09:00"
                    },
                    {
                        "slug":  "money-seo-aipa",
                        "time":  "2026-06-03T20:58:01.8926308+09:00"
                    },
                    {
                        "slug":  "money-dinii-followup",
                        "time":  "2026-06-03T21:01:01.9371908+09:00"
                    },
                    {
                        "slug":  "money-dinii-followup",
                        "time":  "2026-06-03T21:04:02.8075926+09:00"
                    },
                    {
                        "slug":  "money-aipa-email-templates",
                        "time":  "2026-06-03T21:07:01.9671072+09:00"
                    },
                    {
                        "slug":  "money-school-parent-lp",
                        "time":  "2026-06-03T21:10:01.9172443+09:00"
                    },
                    {
                        "slug":  "money-aipa-prospect-list",
                        "time":  "2026-06-03T21:13:01.9532254+09:00"
                    },
                    {
                        "slug":  "money-school-curriculum",
                        "time":  "2026-06-03T21:16:01.9270447+09:00"
                    },
                    {
                        "slug":  "money-contest-yume-award",
                        "time":  "2026-06-03T21:19:02.0045805+09:00"
                    },
                    {
                        "slug":  "money-contest-list",
                        "time":  "2026-06-03T21:22:01.9550690+09:00"
                    },
                    {
                        "slug":  "money-app-niche-hunt",
                        "time":  "2026-06-03T21:25:01.9541766+09:00"
                    },
                    {
                        "slug":  "money-school-trial",
                        "time":  "2026-06-03T21:28:01.9342092+09:00"
                    },
                    {
                        "slug":  "money-seo-aipa",
                        "time":  "2026-06-03T21:31:02.0052882+09:00"
                    },
                    {
                        "slug":  "money-aipax-proposal-template",
                        "time":  "2026-06-03T21:34:01.9995594+09:00"
                    },
                    {
                        "slug":  "money-aipa-email-templates",
                        "time":  "2026-06-03T21:37:01.9605762+09:00"
                    },
                    {
                        "slug":  "money-aipax-prospects",
                        "time":  "2026-06-03T21:40:01.9677746+09:00"
                    },
                    {
                        "slug":  "money-contest-list",
                        "time":  "2026-06-03T21:43:01.9920439+09:00"
                    },
                    {
                        "slug":  "money-contest-list",
                        "time":  "2026-06-03T21:46:02.0219613+09:00"
                    },
                    {
                        "slug":  "money-seo-aipa",
                        "time":  "2026-06-03T21:49:02.0459622+09:00"
                    },
                    {
                        "slug":  "money-aipa-email-templates",
                        "time":  "2026-06-03T21:52:02.0062607+09:00"
                    },
                    {
                        "slug":  "money-aipa-landing-page",
                        "time":  "2026-06-03T21:55:02.0230508+09:00"
                    },
                    {
                        "slug":  "money-twitter-aipax",
                        "time":  "2026-06-03T21:58:02.0160248+09:00"
                    },
                    {
                        "slug":  "money-aipa-email-templates",
                        "time":  "2026-06-03T22:01:02.0439862+09:00"
                    },
                    {
                        "slug":  "money-aipax-proposal-template",
                        "time":  "2026-06-03T22:04:02.0650814+09:00"
                    },
                    {
                        "slug":  "money-seo-aipa",
                        "time":  "2026-06-03T22:07:02.1241743+09:00"
                    },
                    {
                        "slug":  "money-school-curriculum",
                        "time":  "2026-06-03T22:10:02.0548472+09:00"
                    },
                    {
                        "slug":  "money-school-curriculum",
                        "time":  "2026-06-03T22:13:02.0735129+09:00"
                    },
                    {
                        "slug":  "money-aipa-followup-scripts",
                        "time":  "2026-06-03T22:16:02.0694799+09:00"
                    },
                    {
                        "slug":  "money-app-niche-hunt",
                        "time":  "2026-06-03T22:19:02.1012349+09:00"
                    },
                    {
                        "slug":  "money-aipax-proposal-template",
                        "time":  "2026-06-03T22:22:02.0807608+09:00"
                    },
                    {
                        "slug":  "money-contest-yume-award",
                        "time":  "2026-06-03T22:25:02.0729823+09:00"
                    },
                    {
                        "slug":  "money-contest-yume-award",
                        "time":  "2026-06-03T22:28:02.0662631+09:00"
                    },
                    {
                        "slug":  "money-aipa-followup-scripts",
                        "time":  "2026-06-03T22:31:02.1183628+09:00"
                    },
                    {
                        "slug":  "money-school-curriculum",
                        "time":  "2026-06-03T22:34:02.1094537+09:00"
                    },
                    {
                        "slug":  "money-app-spec-1week",
                        "time":  "2026-06-03T22:37:02.0889635+09:00"
                    },
                    {
                        "slug":  "money-twitter-aipax",
                        "time":  "2026-06-03T22:40:02.0859038+09:00"
                    },
                    {
                        "slug":  "money-app-niche-hunt",
                        "time":  "2026-06-03T22:43:02.1167895+09:00"
                    },
                    {
                        "slug":  "money-aipa-prospect-list",
                        "time":  "2026-06-03T22:46:02.1401537+09:00"
                    },
                    {
                        "slug":  "money-seo-aipa",
                        "time":  "2026-06-03T22:49:02.1364457+09:00"
                    },
                    {
                        "slug":  "money-twitter-aipax",
                        "time":  "2026-06-03T22:52:02.1366728+09:00"
                    },
                    {
                        "slug":  "money-school-curriculum",
                        "time":  "2026-06-03T22:55:02.2009243+09:00"
                    },
                    {
                        "slug":  "money-contest-yume-award",
                        "time":  "2026-06-03T22:58:02.1601032+09:00"
                    },
                    {
                        "slug":  "money-aipax-proposal-template",
                        "time":  "2026-06-03T23:01:02.1561611+09:00"
                    },
                    {
                        "slug":  "money-school-parent-lp",
                        "time":  "2026-06-03T23:04:02.1413619+09:00"
                    },
                    {
                        "slug":  "money-twitter-aipax",
                        "time":  "2026-06-03T23:07:02.1758050+09:00"
                    },
                    {
                        "slug":  "money-dinii-followup",
                        "time":  "2026-06-03T23:10:02.1497394+09:00"
                    },
                    {
                        "slug":  "money-seo-aipa",
                        "time":  "2026-06-03T23:13:02.2039121+09:00"
                    },
                    {
                        "slug":  "money-seo-aipa",
                        "time":  "2026-06-03T23:16:02.1930863+09:00"
                    },
                    {
                        "slug":  "money-contest-yume-award",
                        "time":  "2026-06-03T23:19:02.2674366+09:00"
                    },
                    {
                        "slug":  "money-seo-aipa",
                        "time":  "2026-06-03T23:22:02.2277347+09:00"
                    },
                    {
                        "slug":  "money-school-parent-lp",
                        "time":  "2026-06-03T23:25:02.2259155+09:00"
                    },
                    {
                        "slug":  "money-school-parent-lp",
                        "time":  "2026-06-03T23:28:02.2282541+09:00"
                    },
                    {
                        "slug":  "money-app-spec-1week",
                        "time":  "2026-06-03T23:31:02.2925475+09:00"
                    },
                    {
                        "slug":  "money-aipa-followup-scripts",
                        "time":  "2026-06-03T23:34:02.2644794+09:00"
                    },
                    {
                        "slug":  "money-app-niche-hunt",
                        "time":  "2026-06-03T23:37:02.2727284+09:00"
                    },
                    {
                        "slug":  "money-content-school",
                        "time":  "2026-06-03T23:40:02.2611038+09:00"
                    },
                    {
                        "slug":  "money-school-curriculum",
                        "time":  "2026-06-03T23:43:02.2833339+09:00"
                    },
                    {
                        "slug":  "money-aipax-proposal-template",
                        "time":  "2026-06-03T23:46:02.2690628+09:00"
                    },
                    {
                        "slug":  "money-aipa-prospect-list",
                        "time":  "2026-06-03T23:49:02.3340182+09:00"
                    },
                    {
                        "slug":  "money-school-trial",
                        "time":  "2026-06-03T23:52:02.2961457+09:00"
                    },
                    {
                        "slug":  "money-twitter-aipax",
                        "time":  "2026-06-03T23:55:02.3001067+09:00"
                    },
                    {
                        "slug":  "money-content-school",
                        "time":  "2026-06-03T23:58:02.3043325+09:00"
                    },
                    {
                        "slug":  "money-school-curriculum",
                        "time":  "2026-06-04T00:01:02.3080821+09:00"
                    },
                    {
                        "slug":  "money-aipax-proposal-template",
                        "time":  "2026-06-04T00:04:02.3342747+09:00"
                    },
                    {
                        "slug":  "money-aipax-proposal-template",
                        "time":  "2026-06-04T00:07:02.3873269+09:00"
                    },
                    {
                        "slug":  "money-school-parent-lp",
                        "time":  "2026-06-04T00:10:02.3585475+09:00"
                    },
                    {
                        "slug":  "money-school-curriculum",
                        "time":  "2026-06-04T00:13:02.3952997+09:00"
                    },
                    {
                        "slug":  "money-dinii-followup",
                        "time":  "2026-06-04T00:16:02.3588984+09:00"
                    },
                    {
                        "slug":  "money-contest-yume-award",
                        "time":  "2026-06-04T00:19:02.3990477+09:00"
                    },
                    {
                        "slug":  "money-aipa-followup-scripts",
                        "time":  "2026-06-04T00:22:02.3825096+09:00"
                    },
                    {
                        "slug":  "money-content-school",
                        "time":  "2026-06-04T00:25:02.4115643+09:00"
                    },
                    {
                        "slug":  "money-seo-aipa",
                        "time":  "2026-06-04T00:28:02.4235043+09:00"
                    },
                    {
                        "slug":  "money-school-trial",
                        "time":  "2026-06-04T00:31:02.4535874+09:00"
                    },
                    {
                        "slug":  "money-aipa-landing-page",
                        "time":  "2026-06-04T00:34:02.4471059+09:00"
                    },
                    {
                        "slug":  "money-school-curriculum",
                        "time":  "2026-06-04T00:37:02.4429486+09:00"
                    },
                    {
                        "slug":  "money-aipa-landing-page",
                        "time":  "2026-06-04T00:40:02.4549747+09:00"
                    },
                    {
                        "slug":  "money-school-curriculum",
                        "time":  "2026-06-04T00:43:02.4672073+09:00"
                    },
                    {
                        "slug":  "money-app-niche-hunt",
                        "time":  "2026-06-04T00:46:02.4394463+09:00"
                    },
                    {
                        "slug":  "money-aipa-email-templates",
                        "time":  "2026-06-04T00:49:02.4812684+09:00"
                    },
                    {
                        "slug":  "money-aipa-prospect-list",
                        "time":  "2026-06-04T00:52:02.4563033+09:00"
                    },
                    {
                        "slug":  "money-aipax-prospects",
                        "time":  "2026-06-04T00:55:02.4961739+09:00"
                    },
                    {
                        "slug":  "money-app-niche-hunt",
                        "time":  "2026-06-04T00:58:02.4679860+09:00"
                    },
                    {
                        "slug":  "money-twitter-aipax",
                        "time":  "2026-06-04T01:01:02.4865651+09:00"
                    },
                    {
                        "slug":  "money-content-school",
                        "time":  "2026-06-04T01:04:02.4818175+09:00"
                    },
                    {
                        "slug":  "money-aipa-prospect-list",
                        "time":  "2026-06-04T01:07:02.5182085+09:00"
                    },
                    {
                        "slug":  "money-aipax-proposal-template",
                        "time":  "2026-06-04T01:10:02.4985472+09:00"
                    },
                    {
                        "slug":  "money-aipax-prospects",
                        "time":  "2026-06-04T01:13:02.5208849+09:00"
                    },
                    {
                        "slug":  "money-aipa-email-templates",
                        "time":  "2026-06-04T01:16:01.4524208+09:00"
                    },
                    {
                        "slug":  "money-aipax-prospects",
                        "time":  "2026-06-04T01:19:01.5477159+09:00"
                    },
                    {
                        "slug":  "money-school-curriculum",
                        "time":  "2026-06-04T01:22:01.5233347+09:00"
                    },
                    {
                        "slug":  "money-app-niche-hunt",
                        "time":  "2026-06-04T01:25:01.5231266+09:00"
                    },
                    {
                        "slug":  "money-aipa-followup-scripts",
                        "time":  "2026-06-04T01:28:01.5598715+09:00"
                    },
                    {
                        "slug":  "money-twitter-aipax",
                        "time":  "2026-06-04T01:31:01.5814661+09:00"
                    },
                    {
                        "slug":  "money-content-school",
                        "time":  "2026-06-04T01:34:01.5553305+09:00"
                    },
                    {
                        "slug":  "money-aipa-followup-scripts",
                        "time":  "2026-06-04T01:37:01.5730191+09:00"
                    },
                    {
                        "slug":  "money-content-school",
                        "time":  "2026-06-04T01:40:01.5767401+09:00"
                    },
                    {
                        "slug":  "money-app-niche-hunt",
                        "time":  "2026-06-04T01:43:01.5929056+09:00"
                    },
                    {
                        "slug":  "money-twitter-aipax",
                        "time":  "2026-06-04T01:46:01.5948330+09:00"
                    },
                    {
                        "slug":  "money-contest-list",
                        "time":  "2026-06-04T01:49:01.5987168+09:00"
                    },
                    {
                        "slug":  "money-aipa-landing-page",
                        "time":  "2026-06-04T01:52:01.6330806+09:00"
                    },
                    {
                        "slug":  "money-aipa-landing-page",
                        "time":  "2026-06-04T01:55:01.6238951+09:00"
                    },
                    {
                        "slug":  "money-aipa-prospect-list",
                        "time":  "2026-06-04T01:58:01.6364542+09:00"
                    },
                    {
                        "slug":  "money-contest-list",
                        "time":  "2026-06-04T02:01:01.6514107+09:00"
                    },
                    {
                        "slug":  "money-contest-list",
                        "time":  "2026-06-04T02:04:01.6654880+09:00"
                    },
                    {
                        "slug":  "money-contest-list",
                        "time":  "2026-06-04T02:07:01.6606675+09:00"
                    },
                    {
                        "slug":  "money-app-spec-1week",
                        "time":  "2026-06-04T02:10:01.6666380+09:00"
                    },
                    {
                        "slug":  "money-twitter-aipax",
                        "time":  "2026-06-04T02:13:01.6760183+09:00"
                    },
                    {
                        "slug":  "money-content-school",
                        "time":  "2026-06-04T02:16:01.7151878+09:00"
                    },
                    {
                        "slug":  "money-twitter-aipax",
                        "time":  "2026-06-04T02:19:01.7094297+09:00"
                    },
                    {
                        "slug":  "money-twitter-aipax",
                        "time":  "2026-06-04T02:22:01.7048723+09:00"
                    },
                    {
                        "slug":  "money-content-school",
                        "time":  "2026-06-04T02:25:01.7249900+09:00"
                    },
                    {
                        "slug":  "money-aipa-landing-page",
                        "time":  "2026-06-04T02:28:01.7501922+09:00"
                    },
                    {
                        "slug":  "money-aipa-email-templates",
                        "time":  "2026-06-04T02:31:01.7416180+09:00"
                    },
                    {
                        "slug":  "money-app-niche-hunt",
                        "time":  "2026-06-04T02:34:01.7765477+09:00"
                    },
                    {
                        "slug":  "money-aipax-proposal-template",
                        "time":  "2026-06-04T02:37:01.7610713+09:00"
                    },
                    {
                        "slug":  "money-aipa-prospect-list",
                        "time":  "2026-06-04T02:40:01.7810990+09:00"
                    },
                    {
                        "slug":  "money-aipa-email-templates",
                        "time":  "2026-06-04T02:43:01.7659510+09:00"
                    },
                    {
                        "slug":  "money-seo-aipa",
                        "time":  "2026-06-04T02:46:01.7970825+09:00"
                    },
                    {
                        "slug":  "money-dinii-followup",
                        "time":  "2026-06-04T02:49:01.8032817+09:00"
                    },
                    {
                        "slug":  "money-aipax-proposal-template",
                        "time":  "2026-06-04T02:52:01.8687546+09:00"
                    },
                    {
                        "slug":  "money-aipa-email-templates",
                        "time":  "2026-06-04T02:55:01.7949468+09:00"
                    },
                    {
                        "slug":  "money-school-curriculum",
                        "time":  "2026-06-04T02:58:01.8074669+09:00"
                    },
                    {
                        "slug":  "money-contest-list",
                        "time":  "2026-06-04T03:01:01.8196834+09:00"
                    },
                    {
                        "slug":  "money-seo-aipa",
                        "time":  "2026-06-04T03:04:01.8525413+09:00"
                    },
                    {
                        "slug":  "money-school-curriculum",
                        "time":  "2026-06-04T03:07:01.8257377+09:00"
                    },
                    {
                        "slug":  "money-seo-aipa",
                        "time":  "2026-06-04T03:10:01.8711405+09:00"
                    },
                    {
                        "slug":  "money-content-school",
                        "time":  "2026-06-04T03:13:01.8311309+09:00"
                    },
                    {
                        "slug":  "money-app-spec-1week",
                        "time":  "2026-06-04T03:16:01.9004286+09:00"
                    },
                    {
                        "slug":  "money-aipax-prospects",
                        "time":  "2026-06-04T03:19:01.8405963+09:00"
                    },
                    {
                        "slug":  "money-aipa-landing-page",
                        "time":  "2026-06-04T03:22:01.8738162+09:00"
                    },
                    {
                        "slug":  "money-app-spec-1week",
                        "time":  "2026-06-04T03:25:01.8472249+09:00"
                    },
                    {
                        "slug":  "money-aipa-landing-page",
                        "time":  "2026-06-04T03:28:01.8734797+09:00"
                    },
                    {
                        "slug":  "money-contest-list",
                        "time":  "2026-06-04T03:31:01.8665031+09:00"
                    },
                    {
                        "slug":  "money-school-trial",
                        "time":  "2026-06-04T03:34:01.8961299+09:00"
                    },
                    {
                        "slug":  "money-content-school",
                        "time":  "2026-06-04T03:37:01.8783653+09:00"
                    },
                    {
                        "slug":  "money-app-niche-hunt",
                        "time":  "2026-06-04T03:40:01.8952135+09:00"
                    },
                    {
                        "slug":  "money-school-trial",
                        "time":  "2026-06-04T03:43:01.9216565+09:00"
                    },
                    {
                        "slug":  "money-aipax-prospects",
                        "time":  "2026-06-04T03:46:01.9167307+09:00"
                    },
                    {
                        "slug":  "money-seo-aipa",
                        "time":  "2026-06-04T03:49:01.9269850+09:00"
                    },
                    {
                        "slug":  "money-school-trial",
                        "time":  "2026-06-04T03:52:01.9217950+09:00"
                    },
                    {
                        "slug":  "money-aipa-email-templates",
                        "time":  "2026-06-04T03:55:01.9590764+09:00"
                    },
                    {
                        "slug":  "money-dinii-followup",
                        "time":  "2026-06-04T03:58:01.9200249+09:00"
                    },
                    {
                        "slug":  "money-app-niche-hunt",
                        "time":  "2026-06-04T04:01:01.9218126+09:00"
                    },
                    {
                        "slug":  "money-aipa-email-templates",
                        "time":  "2026-06-04T04:04:01.9485108+09:00"
                    },
                    {
                        "slug":  "money-seo-aipa",
                        "time":  "2026-06-04T04:07:01.9664450+09:00"
                    },
                    {
                        "slug":  "money-school-curriculum",
                        "time":  "2026-06-04T04:10:01.9561346+09:00"
                    },
                    {
                        "slug":  "money-school-parent-lp",
                        "time":  "2026-06-04T04:13:01.9527949+09:00"
                    },
                    {
                        "slug":  "money-aipa-landing-page",
                        "time":  "2026-06-04T04:16:02.0401260+09:00"
                    },
                    {
                        "slug":  "money-app-niche-hunt",
                        "time":  "2026-06-04T04:19:01.9996087+09:00"
                    },
                    {
                        "slug":  "money-contest-yume-award",
                        "time":  "2026-06-04T04:22:02.0276157+09:00"
                    },
                    {
                        "slug":  "money-aipa-email-templates",
                        "time":  "2026-06-04T04:25:01.9859229+09:00"
                    },
                    {
                        "slug":  "money-content-school",
                        "time":  "2026-06-04T04:28:02.0041658+09:00"
                    },
                    {
                        "slug":  "money-contest-list",
                        "time":  "2026-06-04T04:31:02.0931120+09:00"
                    },
                    {
                        "slug":  "money-aipax-proposal-template",
                        "time":  "2026-06-04T04:34:02.0140940+09:00"
                    },
                    {
                        "slug":  "money-school-curriculum",
                        "time":  "2026-06-04T04:37:02.0009598+09:00"
                    },
                    {
                        "slug":  "money-dinii-followup",
                        "time":  "2026-06-04T04:40:01.9940540+09:00"
                    },
                    {
                        "slug":  "money-seo-aipa",
                        "time":  "2026-06-04T04:43:02.0391246+09:00"
                    },
                    {
                        "slug":  "money-contest-list",
                        "time":  "2026-06-04T04:46:02.0460021+09:00"
                    },
                    {
                        "slug":  "money-aipa-followup-scripts",
                        "time":  "2026-06-04T04:49:02.0356275+09:00"
                    },
                    {
                        "slug":  "money-contest-yume-award",
                        "time":  "2026-06-04T04:52:02.0546830+09:00"
                    },
                    {
                        "slug":  "money-app-spec-1week",
                        "time":  "2026-06-04T04:55:02.0760596+09:00"
                    },
                    {
                        "slug":  "money-school-parent-lp",
                        "time":  "2026-06-04T04:58:02.0763831+09:00"
                    }
                ]
}